<annotation>
	<folder>Fiddle _ Google Search</folder>
	<filename>File174.jpg</filename>
	<path>/Users/gourav/Downloads/ML/Fiddle _ Google Search/File174.jpg</path>
	<source>
		<database>Unknown</database>
	</source>
	<size>
		<width>560</width>
		<height>323</height>
		<depth>3</depth>
	</size>
	<segmented>0</segmented>
	<object>
		<name>Fiddle</name>
		<pose>Unspecified</pose>
		<truncated>0</truncated>
		<difficult>0</difficult>
		<bndbox>
			<xmin>25</xmin>
			<ymin>21</ymin>
			<xmax>550</xmax>
			<ymax>288</ymax>
		</bndbox>
	</object>
</annotation>
