<annotation>
	<folder>Grand Piano _ Google Search</folder>
	<filename>File192.jpg</filename>
	<path>/Users/gourav/Downloads/ML/Grand Piano _ Google Search/File192.png</path>
	<source>
		<database>Unknown</database>
	</source>
	<size>
		<width>1600</width>
		<height>1876</height>
		<depth>3</depth>
	</size>
	<segmented>0</segmented>
	<object>
		<name>GrandPiano</name>
		<pose>Unspecified</pose>
		<truncated>0</truncated>
		<difficult>0</difficult>
		<bndbox>
			<xmin>105</xmin>
			<ymin>218</ymin>
			<xmax>1599</xmax>
			<ymax>952</ymax>
		</bndbox>
	</object>
</annotation>
