<annotation>
	<folder>ZEBRA _ Google Search</folder>
	<filename>File641.jpg</filename>
	<path>/Users/gourav/Downloads/ML/ZEBRA _ Google Search/File641.jpg</path>
	<source>
		<database>Unknown</database>
	</source>
	<size>
		<width>877</width>
		<height>500</height>
		<depth>3</depth>
	</size>
	<segmented>0</segmented>
	<object>
		<name>Zebra</name>
		<pose>Unspecified</pose>
		<truncated>0</truncated>
		<difficult>0</difficult>
		<bndbox>
			<xmin>186</xmin>
			<ymin>11</ymin>
			<xmax>761</xmax>
			<ymax>440</ymax>
		</bndbox>
	</object>
</annotation>
